Workbook
Name TauxTVA: 'Paramètres'!$C$7

Sheet Couverture
B2: ÉDITION DÉCOUVERTE · GRATUITE
B4: Poser les bases
B10: Le carnet Excel qui lit tes formules
B12: Camille dirige Le Zinc de Léon, brasserie familiale depuis 1958. Excel est son outil de tous les jours : commandes, marges, planning, caisse. Chaque réponse est corrigée toute seule.
B18: 1 | F18: 6 | J18: 10 min
B22: défi d'essai, gratuit | F22: contrôles qui corrigent tes réponses | J22: pour découvrir la méthode
B24: Joffrey Gros · XcelUrself | J24: Commencer →
B26: Formateur Excel, Power Query et Power BI · Microsoft Certified Trainer

Sheet Accueil
B2: Comment ça marche
B6: Trois gestes, et un retour immédiat à chaque réponse.
B8: Le Zinc de Léon, depuis 1958
B10: Léon a ouvert son zinc en 1958. Sa petite-fille Camille a repris la brasserie en 2019. Excel est son outil de tous les jours : elle y fait ses achats, sa carte et ses marges, ses stocks, son planning et sa caisse. C'est avec elle que tu vas apprendre.
B14: Achats | D14: Carte & marges | F14: Stocks | H14: Planning | J14: Caisse | L14: Bons de commande
B20: 1 · Lis | F20: 2 · Fais | J20: 3 · Vérifie
B22: Chaque défi raconte une scène de la brasserie, puis pose quelques questions courtes. | F22: Réponds dans les cases à bordure verte, avec des formules : jamais de résultat tapé à la main. | J22: Le contrôle te répond tout de suite. Tu peux recommencer autant que tu veux.
B26: Le point de départ de tout
B28: Un tableau structuré
B30: Toutes les données de ce carnet sont des tableaux Excel. Ils portent un nom, grandissent tout seuls et rendent les formules lisibles : Achats[Montant HT] plutôt que F13:F20.
B34: ✔ | F34: ✘ valeur | J34: ✘ formule
B36: C'est juste. | F36: Le résultat n'est pas le bon : l'indice du chef te met sur la piste. | J36: Bon résultat, mais tapé à la main : écris une formule.
B40: Un indice ? | H40: Ton grade
B42: Dans chaque défi, choisis « Voir » dans la colonne Indice. Il coûte 1 point : à toi de juger si tu en as besoin. | H42: Commis, puis Chef de partie dès 50 % du score, puis Chef de cuisine dès 80 %.
B46: Avant de commencer | J46: Ici, des formules classiques. Le carnet complet ajoute RECHERCHEX : il demande Excel 2021, 2024 ou Microsoft 365.
B48: Si Excel affiche un bandeau jaune, clique sur « Activer la modification » : sans cela, les contrôles ne se calculent pas.
B52: Ouvrir la carte des défis →

Sheet Menu
C1: ← Accueil | G1: Défi 1 →
B2: La carte des défis
B4: =IF(TRIM(D5)="","① Commence ici : écris ton prénom et ton nom dans la case ci-dessous.",IF(G8<6,HYPERLINK("#'D01'!A1","▶ Commence ici : Défi 1 · La mise en place →"),HYPERLINK("#Bilan!A1","🎉 Le défi est réussi · voir mon bilan →")))
B5: =IF(TRIM(D5)="","ÉTAPE 1 · Écris ton prénom et ton nom : tes chiffres en dépendent.","✔ Étape 1 faite · bonjour "&TRIM(D5)&" !") | D5: Alex Martin
B7: N° | C7: Défi | D7: Bloc | E7: Durée | F7: Aller | G7: Score
B8: 1 | C8: La mise en place | D8: Bloc A · Structurer | E8: 10 min | F8: Y aller → | G8: =MAX(0,COUNTIF(_ctl!$C$2:$C$7,"✔")-COUNTIF('D01'!$L$28:$L$33,"Voir"))
B10: SCORE TOTAL (indices déduits) | G10: =SUM(G8:G8)
C15: Mon bilan →
C16: Aide & licence →

Sheet D01
E1: ⌂ Menu | H1: Bilan → | N1: =IF(TRIM(Menu!$D$5)="",0,1)
B2: LE ZINC DE LÉON · DÉFI 01 / 04 · BLOC A · STRUCTURER | G2: Aller aux questions ↓
B3: La mise en place
B4: Le Zinc de Léon, c'est trois services par jour et un classeur Excel ouvert en permanence : c'est l'outil de tous les jours de Camille. Ce matin, elle vérifie les achats : tu poses les premiers calculs, comme on prépare ses bacs, proprement et sans rien recopier à la main.
B5: « Un chiffre tapé à la main, c'est une erreur qui attend le service du soir. » · Camille
B7: =IF($N$1=0,HYPERLINK("#Menu!D5","✏️ Pense à écrire ton prénom dans le Menu (étape 1) : clique ici. Tes données seront alors personnalisées. →"),IF(COUNTIF(J28:J34,"✔")=6,HYPERLINK("#'Bilan'!A1","🎉 Défi réussi ! Passe à ton bilan →"),COUNTIF(J28:J34,"✔")&" / 6 questions réussies · continue, une réponse à la fois."))
B9: RAPPEL | C9: Les données sont dans des tableaux Excel : clique sur une colonne et Excel écrit Achats[Montant HT] pour toi. Une formule commence toujours par =. Un nom (TauxTVA) évite de retaper un taux.
B11: DONNÉES · Les achats du matin (les quantités sont propres à ton carnet) ▦ tableau « Achats »
C12: Produit | D12: Quantité (kg) | E12: Prix au kg | F12: Montant HT
C13: Pommes de terre | D13: =25+MOD(_ref!$Z$1,5) | E13: 1.1 | F13: =ROUND(Achats[[#This Row],[Quantité (kg)]]*Achats[[#This Row],[Prix au kg]],2)
C14: Oignons | D14: =10+MOD(_ref!$Z$1,7) | E14: 1.4 | F14: =ROUND(Achats[[#This Row],[Quantité (kg)]]*Achats[[#This Row],[Prix au kg]],2)
C15: Carottes | D15: =12+MOD(_ref!$Z$1,9) | E15: 1.25 | F15: =ROUND(Achats[[#This Row],[Quantité (kg)]]*Achats[[#This Row],[Prix au kg]],2)
C16: Poulet fermier | D16: =18+MOD(_ref!$Z$1,11) | E16: 7.8 | F16: =ROUND(Achats[[#This Row],[Quantité (kg)]]*Achats[[#This Row],[Prix au kg]],2)
C17: Entrecôte | D17: =9+MOD(_ref!$Z$1,13) | E17: 21.5 | F17: =ROUND(Achats[[#This Row],[Quantité (kg)]]*Achats[[#This Row],[Prix au kg]],2)
C18: Beurre | D18: =6+MOD(_ref!$Z$1,6) | E18: 9.2 | F18: =ROUND(Achats[[#This Row],[Quantité (kg)]]*Achats[[#This Row],[Prix au kg]],2)
C19: Crème | D19: =8+MOD(_ref!$Z$1,8) | E19: 4.1 | F19: =ROUND(Achats[[#This Row],[Quantité (kg)]]*Achats[[#This Row],[Prix au kg]],2)
C20: Champignons | D20: =7+MOD(_ref!$Z$1,10) | E20: 6.3 | F20: =ROUND(Achats[[#This Row],[Quantité (kg)]]*Achats[[#This Row],[Prix au kg]],2)
C22: TVA applicable (denrées) | D22: ='Paramètres'!$C$7
C23: → Aller à la cellule du taux de TVA (feuille Paramètres)
B25: 💡 | C25: =IF(COUNTIF(L28:L33,"Voir")=0,"Indice : aucun demandé. Pour en lire un, choisis « Voir » dans la case ▾ Indice de la question (−1 point) : il s'affichera ici.",IF(L28="Voir","Question 1 : SOMME s'écrit =SOMME( puis tu cliques sur la colonne Montant HT du tableau Achats : Excel écrit tout seul Achats[Montant HT]. ","")&IF(L29="Voir","Question 2 : MOYENNE fonctionne comme SOMME : =MOYENNE(Achats[Montant HT]). ","")&IF(L30="Voir","Question 3 : MAX renvoie le plus grand nombre d'une plage. ","")&IF(L31="Voir","Question 4 : NB compte les cellules qui contiennent un nombre : =NB(plage). ","")&IF(L32="Voir","Question 5 : Lien sous le tableau, feuille Paramètres : clique sur la cellule à bordure verte, tape TauxTVA dans la zone Nom (à gauche de la barre de formule), puis Entrée. ","")&IF(L33="Voir","Question 6 : Ton total HT est dans la case de la question 1. Multiplie-le par (1 + TauxTVA). ",""))
B27: N° | C27: À TOI DE JOUER | G27: TA RÉPONSE | H27: ATTENDU | J27: CONTRÔLE | L27: INDICE ▾ (−1 pt)
B28: =IF($J28="✔","✔",1) | C28: Calcule le total HT des achats du matin (somme de la colonne Montant HT du tableau Achats). Écris une formule, pas le résultat. | G28: =SUM(Achats[Montant HT]) | H28: =IF(LEFT(J28,1)="✘",_ctl!D2,"Un montant en € (formule)") | J28: =_ctl!C2 | L28: ▾ Indice
B29: =IF($J29="✔","✔",2) | C29: Quel est le montant moyen par produit ? | G29: =AVERAGE(Achats[Montant HT]) | H29: =IF(LEFT(J29,1)="✘",_ctl!D3,"Un montant en € (formule)") | J29: =_ctl!C3 | L29: ▾ Indice
B30: =IF($J30="✔","✔",3) | C30: Quel est le montant le plus élevé ? | G30: =MAX(Achats[Montant HT]) | H30: =IF(LEFT(J30,1)="✘",_ctl!D4,"Un montant en € (formule)") | J30: =_ctl!C4 | L30: ▾ Indice
B31: =IF($J31="✔","✔",4) | C31: Combien de produits ont été achetés ? (compte les lignes, ne tape pas 8) | G31: =COUNT(Achats[Montant HT]) | H31: =IF(LEFT(J31,1)="✘",_ctl!D5,"Un nombre (formule)") | J31: =_ctl!C5 | L31: ▾ Indice
B32: =IF($J32="✔","✔",5) | C32: Bonne pratique : donne le nom TauxTVA à la cellule du taux de TVA. Clique sur le lien sous le tableau : il t'emmène sur la feuille Paramètres, où tu sélectionnes la cellule à bordure verte et tapes le nom dans la zone Nom (à gauche de la barre de formule). Rien à écrire dans la case. | G32: voir zone Nom | H32: =IF(LEFT(J32,1)="✘",_ctl!D6,"La cellule du taux nommée TauxTVA") | J32: =_ctl!C6 | L32: ▾ Indice
B33: =IF($J33="✔","✔",6) | C33: Calcule le total TTC avec le nom : total HT × (1 + TauxTVA). Un nom parle mieux qu'une adresse comme D20. | G33: =G28*(1+TauxTVA) | H33: =IF(LEFT(J33,1)="✘",_ctl!D7,"Un montant en € (formule avec TauxTVA)") | J33: =_ctl!C7 | L33: ▾ Indice
B36: SCORE DU DÉFI | J36: =MAX(0,COUNTIF(J28:J34,"✔")-COUNTIF(L28:L34,"Voir"))

Sheet Bilan
C1: ← Défi 1 | E1: ⌂ Menu | H1: Aide →
B2: BILAN
B3: ="Bilan · "&IF(Menu!D5="","(nom non renseigné)",Menu!D5)
B5: SCORE | D5: RÉUSSITE | F5: GRADE | H5: TRAITÉES
B6: =SUM(E9:E9) | D6: =B6/6 | F6: =IF(D6>=0.8,"Chef de cuisine",IF(D6>=0.5,"Chef de partie","Commis")) | H6: =ROWS(_ctl!$C$2:$C$7)-COUNTIF(_ctl!$C$2:$C$7,"·")
B8: N° | C8: Défi | D8: Bloc | E8: Score | F8: Sur | G8: % | H8: ✘ formule | I8: ✘ valeur | J8: Pas répondu | K8: Affichage modifié | L8: Indices
B9: 1 | C9: La mise en place | D9: Bloc A | E9: =MAX(0,COUNTIF(_ctl!$C$2:$C$7,"✔")-COUNTIF('D01'!$L$28:$L$33,"Voir")) | F9: 6 | G9: =E9/F9 | H9: =COUNTIF(_ctl!$C$2:$C$7,"✘ formule") | I9: =COUNTIF(_ctl!$C$2:$C$7,"✘ valeur")+COUNTIF(_ctl!$C$2:$C$7,"✘") | J9: =COUNTIF(_ctl!$C$2:$C$7,"·") | K9: =IF(TRIM(Menu!$D$5)="",0,SUMPRODUCT(--('D01'!J28:J33<>_ctl!$C$2:$C$7))) | L9: =COUNTIF('D01'!$L$28:$L$33,"Voir")
B11: Édition découverte : le carnet complet ajoute 3 défis et un bonus d'enquête.
B13: L'ARDOISE DU JOUR · TON TRAVAIL, AU TABLEAU
B14: ="Le Zinc de Léon · achats du matin · "&IF(TRIM(Menu!$D$5)="","chef",TRIM(Menu!$D$5))
B15: ="Total HT du matin ........ "&IF(_ctl!$C$2="✔",FIXED('D01'!G28,2)&" €","à calculer")
B16: ="Montant moyen par produit ........ "&IF(_ctl!$C$3="✔",FIXED('D01'!G29,2)&" €","à calculer")
B17: ="Plus gros poste ........ "&IF(_ctl!$C$4="✔",FIXED('D01'!G30,2)&" €","à calculer")
B18: ="Total TTC (TauxTVA) ........ "&IF(_ctl!$C$7="✔",FIXED('D01'!G33,2)&" €","à calculer")
B19: ="Camille : "&IF(COUNTIF(_ctl!$C$2:$C$7,"✔")=6,"« Le compte est bon, "&IF(TRIM(Menu!$D$5)="","chef",TRIM(Menu!$D$5))&" ! Bienvenue en cuisine. »","« Continue, "&IF(TRIM(Menu!$D$5)="","chef",TRIM(Menu!$D$5))&" : le service n'est pas fini. »")
B21: ET MAINTENANT ?
B22: Une question, un souci, la licence → Aide | G22: Ce carnet t'a plu ? Dis-le autour de toi : il est gratuit, et le carnet complet poursuit l'aventure.
B23: Le carnet complet « Poser les bases » : 4 défis + 1 bonus, RECHERCHEX, un bon de commande réaliste et 28 contrôles. Lien sur la page où tu as récupéré ce carnet.

Sheet Aide
C1: ← Bilan | F1: ⌂ Menu
B2: AIDE & LICENCE
B3: Un souci ? Les réponses d'abord
B4: Les sept questions que l'on se pose le plus souvent, puis la licence d'utilisation et le moyen de nous écrire.
B6: ? | C6: Les contrôles restent vides ou affichent une erreur.
C7: Excel ouvre souvent les fichiers reçus en mode protégé. Clique sur « Activer la modification » dans le bandeau en haut, puis appuie sur F9 si les contrôles ne se mettent pas à jour.
B8: ? | C8: Le contrôle affiche « ✘ formule » alors que mon résultat est juste.
C9: Tu as tapé le résultat. Le carnet attend une formule, qui commence par = et se recalcule quand les données changent.
B10: ? | C10: Le contrôle affiche « ✘ valeur ».
C11: Lis le message dans la colonne ATTENDU : il décrit l'erreur la plus fréquente. Vérifie aussi la plage (toute la colonne, sans le titre) et les $ des références fixes.
B12: ? | C12: Mes chiffres ne sont pas les mêmes que ceux d'une autre personne.
C13: C'est voulu : les données dépendent du prénom écrit dans le Menu. Si tu changes de prénom, les données changent et tes réponses sont à refaire.
B14: ? | C14: RECHERCHEX n'est pas reconnue.
C15: Elle existe dans Excel 2021, 2024 et Microsoft 365. Excel 2019 et les versions plus anciennes ne la connaissent pas.
B16: ? | C16: Je veux recommencer un défi.
C17: Efface le contenu des cases à bordure verte : les contrôles repartent de zéro. Remets aussi les cases Indice sur « ▾ Indice ».
B18: ? | C18: Je ne peux pas modifier une cellule.
C19: Seules les cases à bordure verte, les cases Indice et ton prénom sont modifiables. Le reste est protégé pour que le carnet ne se casse pas.
B21: LICENCE D'UTILISATION
B22: ="Licence individuelle · licencié à : "&IF(TRIM(Menu!$D$5)="","(écris ton prénom dans le Menu)",TRIM(Menu!$D$5))
B23: Ce carnet est à ton usage personnel. Merci de ne pas le partager ni le revendre : un carnet acheté fait vivre le prochain. © Joffrey Gros · XcelUrself.
B24: UNE QUESTION, UN BUG, UNE IDÉE ?
B25: Écris à mr.grosj@gmail.com (clique ici) : dis quel défi, quelle question, et ce que tu vois à l'écran (une capture aide beaucoup).

Sheet Paramètres
B1: ← Défi 1 | D1: ⌂ Menu
B2: PARAMÈTRES · LE TIROIR DE CAMILLE
B3: Les paramètres
B4: Un taux, un seuil : on le range dans une cellule, puis on lui donne un nom. Cette feuille n'est pas protégée, pour que tu puisses nommer la cellule du taux de TVA (défi 1, question 5).
B6: PARAMÈTRE | C6: VALEUR | D6: NOM À LUI DONNER
B7: TVA applicable (denrées) | C7: 0.055 | D7: TauxTVA (zone Nom, puis Entrée)
B9: Une fois le nom créé, retourne au défi 1 : tu peux l'utiliser dans tes formules.

Sheet _ctl
A2: D01 | B2: 1 | C2: =IFERROR(IF('D01'!G28="","·",IF(AND(ISNUMBER('D01'!G28),ABS('D01'!G28-SUMPRODUCT(ROUND('D01'!$D$13:$D$20*'D01'!$E$13:$E$20,2)))<=0.01),IF(AND(_xlfn.ISFORMULA('D01'!G28),IFERROR(OR(ISNUMBER(SEARCH("F13",_xlfn.FORMULATEXT('D01'!G28))),ISNUMBER(SEARCH("F$13",_xlfn.FORMULATEXT('D01'!G28))),ISNUMBER(SEARCH("Achats[",_xlfn.FORMULATEXT('D01'!G28)))),FALSE)),"✔","✘ formule"),"✘ valeur")),"✘ valeur") | D2: =IFERROR(IF(C2="✘ formule","Bon résultat, mais tapé à la main : écris une formule (et le nom TauxTVA pour le TTC).",IF(C2="✘ valeur",IF(ABS('D01'!G28-(SUM('D01'!$D$13:$D$20)))<0.01,"Tu as additionné les quantités. Il faut la colonne Montant HT.",IF(ABS('D01'!G28-(SUMPRODUCT(ROUND('D01'!$D$13:$D$20*'D01'!$E$13:$E$20,2))*(1+0.055)))<0.01,"Tu as déjà ajouté la TVA. Ici on veut le total HT.",IF(ABS('D01'!G28-(AVERAGE('D01'!$F$13:$F$20)))<0.01,"Tu as calculé une moyenne. On attend la somme.","Vérifie la plage : toute la colonne, sans la ligne de titre."))),"")),"")
A3: D01 | B3: 2 | C3: =IFERROR(IF('D01'!G29="","·",IF(AND(ISNUMBER('D01'!G29),ABS('D01'!G29-(SUMPRODUCT(ROUND('D01'!$D$13:$D$20*'D01'!$E$13:$E$20,2))/ROWS('D01'!$F$13:$F$20)))<=0.01),IF(AND(_xlfn.ISFORMULA('D01'!G29),IFERROR(OR(ISNUMBER(SEARCH("F13",_xlfn.FORMULATEXT('D01'!G29))),ISNUMBER(SEARCH("F$13",_xlfn.FORMULATEXT('D01'!G29))),ISNUMBER(SEARCH("Achats[",_xlfn.FORMULATEXT('D01'!G29)))),FALSE)),"✔","✘ formule"),"✘ valeur")),"✘ valeur") | D3: =IFERROR(IF(C3="✘ formule","Bon résultat, mais tapé à la main : écris une formule (et le nom TauxTVA pour le TTC).",IF(C3="✘ valeur",IF(ABS('D01'!G29-(SUMPRODUCT(ROUND('D01'!$D$13:$D$20*'D01'!$E$13:$E$20,2))))<0.01,"Tu as donné la somme. On attend la moyenne.",IF(ABS('D01'!G29-(MAX('D01'!$F$13:$F$20)))<0.01,"Tu as donné le maximum. On attend la moyenne.","Vérifie la plage : toute la colonne, sans la ligne de titre.")),"")),"")
A4: D01 | B4: 3 | C4: =IFERROR(IF('D01'!G30="","·",IF(AND(ISNUMBER('D01'!G30),ABS('D01'!G30-MAX('D01'!$F$13:$F$20))<=0.01),IF(AND(_xlfn.ISFORMULA('D01'!G30),IFERROR(OR(ISNUMBER(SEARCH("F13",_xlfn.FORMULATEXT('D01'!G30))),ISNUMBER(SEARCH("F$13",_xlfn.FORMULATEXT('D01'!G30))),ISNUMBER(SEARCH("Achats[",_xlfn.FORMULATEXT('D01'!G30)))),FALSE)),"✔","✘ formule"),"✘ valeur")),"✘ valeur") | D4: =IFERROR(IF(C4="✘ formule","Bon résultat, mais tapé à la main : écris une formule (et le nom TauxTVA pour le TTC).",IF(C4="✘ valeur",IF(ABS('D01'!G30-(MIN('D01'!$F$13:$F$20)))<0.01,"Tu as donné le minimum. On attend le maximum.",IF(ABS('D01'!G30-(SUMPRODUCT(ROUND('D01'!$D$13:$D$20*'D01'!$E$13:$E$20,2))))<0.01,"Tu as donné la somme. On attend le plus grand montant.","Vérifie la plage : toute la colonne, sans la ligne de titre.")),"")),"")
A5: D01 | B5: 4 | C5: =IFERROR(IF('D01'!G31="","·",IF(AND(ISNUMBER('D01'!G31),ABS('D01'!G31-ROWS('D01'!$F$13:$F$20))<=0.01),IF(AND(_xlfn.ISFORMULA('D01'!G31),IFERROR(OR(ISNUMBER(SEARCH("(",_xlfn.FORMULATEXT('D01'!G31)))),FALSE)),"✔","✘ formule"),"✘ valeur")),"✘ valeur") | D5: =IFERROR(IF(C5="✘ formule","Bon résultat, mais tapé à la main : écris une formule (et le nom TauxTVA pour le TTC).",IF(C5="✘ valeur",IF(ABS('D01'!G31-(ROWS('D01'!$F$13:$F$20)+1))<0.01,"Tu as compté le titre aussi. NB ignore le texte, pas NBVAL.",IF(ABS('D01'!G31-(SUMPRODUCT(ROUND('D01'!$D$13:$D$20*'D01'!$E$13:$E$20,2))))<0.01,"Tu as additionné. Il faut compter les lignes.","Vérifie la plage : toute la colonne, sans la ligne de titre.")),"")),"")
A6: D01 | B6: 5 | C6: =IFERROR(IF(AND(ROW(INDIRECT("TauxTVA"))=ROW('Paramètres'!$C$7),COLUMN(INDIRECT("TauxTVA"))=COLUMN('Paramètres'!$C$7)),"✔","✘ valeur"),"·") | D6: =IFERROR(IF(C6="✘ formule","Bon résultat, mais tapé à la main : écris une formule (et le nom TauxTVA pour le TTC).",IF(C6="✘ valeur","Le nom existe mais ne pointe pas sur la cellule de TVA (colonne D).","")),"")
A7: D01 | B7: 6 | C7: =IFERROR(IF('D01'!G33="","·",IF(AND(ISNUMBER('D01'!G33),ABS('D01'!G33-(SUMPRODUCT(ROUND('D01'!$D$13:$D$20*'D01'!$E$13:$E$20,2))*(1+'Paramètres'!$C$7)))<=0.01),IF(AND(_xlfn.ISFORMULA('D01'!G33),IFERROR(OR(ISNUMBER(SEARCH("TauxTVA",_xlfn.FORMULATEXT('D01'!G33)))),FALSE)),"✔","✘ formule"),"✘ valeur")),"✘ valeur") | D7: =IFERROR(IF(C7="✘ formule","Bon résultat, mais tapé à la main : écris une formule (et le nom TauxTVA pour le TTC).",IF(C7="✘ valeur",IF(ABS('D01'!G33-(SUMPRODUCT(ROUND('D01'!$D$13:$D$20*'D01'!$E$13:$E$20,2))*0.055))<0.01,"Tu as calculé la TVA seule. Il faut le total TTC : HT + TVA.",IF(ABS('D01'!G33-(SUMPRODUCT(ROUND('D01'!$D$13:$D$20*'D01'!$E$13:$E$20,2))*(1+0.055*100)))<0.01,"Tu as mis 5,5 au lieu de 0,055. Un taux en % vaut un centième.",IF(ABS('D01'!G33-(SUMPRODUCT(ROUND('D01'!$D$13:$D$20*'D01'!$E$13:$E$20,2))))<0.01,"Tu as oublié d'ajouter la TVA.","Vérifie la plage : toute la colonne, sans la ligne de titre."))),"")),"")

Sheet _ref
Z1: =IFERROR(MOD(SUMPRODUCT(_xlfn.UNICODE(MID(TRIM(Menu!$D$5),ROW(INDIRECT("1:"&LEN(TRIM(Menu!$D$5)))),1))*ROW(INDIRECT("1:"&LEN(TRIM(Menu!$D$5))))),99991),0)
